llm_huggingface_plugin.py
llm_huggingface_plugin-0.1.dist-info/licenses/LICENSE
llm_huggingface_plugin-0.1.dist-info/METADATA
llm_huggingface_plugin-0.1.dist-info/WHEEL
llm_huggingface_plugin-0.1.dist-info/entry_points.txt
llm_huggingface_plugin-0.1.dist-info/top_level.txt
llm_huggingface_plugin-0.1.dist-info/RECORD
