Metadata-Version: 2.4
Name: llm-huggingface-plugin
Version: 0.1
Summary: LLM plugin to access Hugging Face models
Author: Katie Mulliken
License-Expression: Apache-2.0
Project-URL: Homepage, https://github.com/SecKatie/llm-huggingface
Project-URL: Changelog, https://github.com/SecKatie/llm-huggingface/releases
Project-URL: Issues, https://github.com/SecKatie/llm-huggingface/issues
Project-URL: CI, https://github.com/SecKatie/llm-huggingface/actions
License-File: LICENSE
Requires-Dist: llm>=0.27.1
Requires-Dist: httpx
Requires-Dist: ijson
Requires-Dist: huggingface-hub[inference]>=0.34.4
Provides-Extra: test
Requires-Dist: pytest; extra == "test"
Requires-Dist: pytest-recording; extra == "test"
Requires-Dist: pytest-asyncio; extra == "test"
Requires-Dist: nest-asyncio; extra == "test"
Requires-Dist: cogapp; extra == "test"
Dynamic: license-file
